databases/__init__.py
databases/__version__.py
databases/database.py
jarudaDB-0.0.3.dist-info/METADATA
jarudaDB-0.0.3.dist-info/WHEEL
jarudaDB-0.0.3.dist-info/top_level.txt
jarudaDB-0.0.3.dist-info/RECORD
