Metadata-Version: 2.1
Name: jarudaDB
Version: 0.0.3
Summary: mysql connector python database module
Home-page: https://github.com/jaruda-88
Author: jaruda
Author-email: jaruda88@gmail.com
License: MIT
Platform: UNKNOWN
Classifier: Development Status :: 5 - Production/Stable
Classifier: Intended Audience :: Developers
Classifier: Topic :: Scientific/Engineering :: Artificial Intelligence
Classifier: Topic :: Scientific/Engineering :: Visualization
Classifier: License :: OSI Approved :: MIT License
Classifier: Programming Language :: Python :: 3.6
Classifier: Operating System :: OS Independent
Requires-Python: >=3
Requires-Dist: mysql-connector-python (==8.0.29)
